setup.py
apps/__init__.py
apps/app.py
apps/forms.py
apps/models.py
apps/settings.py
apps/authapp/__init__.py
apps/authapp/forms.py
apps/authapp/views.py
apps/pictapp/__init__.py
apps/pictapp/forms.py
apps/pictapp/models.py
apps/pictapp/views.py
spotify_share_project.egg-info/PKG-INFO
spotify_share_project.egg-info/SOURCES.txt
spotify_share_project.egg-info/dependency_links.txt
spotify_share_project.egg-info/requires.txt
spotify_share_project.egg-info/top_level.txt