Metadata-Version: 2.1
Name: spotify-share-project
Version: 0.1
Summary: To share playlist
Author: karaage0000
Author-email: karaagekun0451@gmail.com
